ragscore/__init__.py
ragscore/cli.py
ragscore/config.py
ragscore/data_processing.py
ragscore/evaluation.py
ragscore/exceptions.py
ragscore/llm.py
ragscore/mcp_server.py
ragscore/pipeline.py
ragscore/quick_test.py
ragscore/ui.py
ragscore/providers/__init__.py
ragscore/providers/anthropic_provider.py
ragscore/providers/base.py
ragscore/providers/dashscope_provider.py
ragscore/providers/factory.py
ragscore/providers/generic_provider.py
ragscore/providers/ollama_provider.py
ragscore/providers/openai_provider.py
ragscore-0.6.3.dist-info/licenses/LICENSE
ragscore-0.6.3.dist-info/METADATA
ragscore-0.6.3.dist-info/WHEEL
ragscore-0.6.3.dist-info/entry_points.txt
ragscore-0.6.3.dist-info/top_level.txt
ragscore-0.6.3.dist-info/RECORD
