Metadata-Version: 2.4
Name: ragscore
Version: 0.6.3
Summary: The '1-Minute RAG Audit' - Generate QA datasets & evaluate RAG systems in Colab, Jupyter, or CLI. Privacy-first, async, visual reports.
Author-email: RAGScore Team <team@ragscore.io>
License: Apache-2.0
Project-URL: Homepage, https://github.com/HZYAI/RagScore
Project-URL: Documentation, https://github.com/HZYAI/RagScore#readme
Project-URL: Repository, https://github.com/HZYAI/RagScore
Project-URL: Changelog, https://github.com/HZYAI/RagScore/blob/main/CHANGELOG.md
Project-URL: Bug Tracker, https://github.com/HZYAI/RagScore/issues
Keywords: rag,rag-evaluation,qa-generation,llm,llm-as-judge,local-llm,ollama,jupyter,colab,notebook,visualization,mcp,llmops,async,privacy,synthetic-data,evaluation,ai-evaluation
Classifier: Development Status :: 4 - Beta
Classifier: Intended Audience :: Developers
Classifier: Intended Audience :: Science/Research
Classifier: License :: OSI Approved :: Apache Software License
Classifier: Operating System :: OS Independent
Classifier: Programming Language :: Python :: 3
Classifier: Programming Language :: Python :: 3.9
Classifier: Programming Language :: Python :: 3.10
Classifier: Programming Language :: Python :: 3.11
Classifier: Programming Language :: Python :: 3.12
Classifier: Topic :: Scientific/Engineering :: Artificial Intelligence
Classifier: Topic :: Text Processing :: Linguistic
Requires-Python: <3.13,>=3.9
License-File: LICENSE
Requires-Dist: pypdf2>=3.0.1
Requires-Dist: nltk>=3.8.1
Requires-Dist: tqdm>=4.66.1
Requires-Dist: typer[all]>=0.16.0
Requires-Dist: python-dotenv>=1.0.0
Requires-Dist: aiohttp>=3.9.0
Provides-Extra: openai
Requires-Dist: openai>=1.0.0; extra == "openai"
Provides-Extra: anthropic
Requires-Dist: anthropic>=0.18.0; extra == "anthropic"
Provides-Extra: dashscope
Requires-Dist: dashscope>=1.14.1; extra == "dashscope"
Provides-Extra: providers
Requires-Dist: ragscore[anthropic,dashscope,openai]; extra == "providers"
Provides-Extra: notebook
Requires-Dist: nest_asyncio>=1.5.0; extra == "notebook"
Requires-Dist: pandas>=2.0.0; extra == "notebook"
Provides-Extra: mcp
Requires-Dist: mcp>=1.0.0; extra == "mcp"
Provides-Extra: all
Requires-Dist: ragscore[notebook,providers]; extra == "all"
Provides-Extra: dev
Requires-Dist: pytest>=7.4.3; extra == "dev"
Requires-Dist: pytest-cov>=4.1.0; extra == "dev"
Requires-Dist: pytest-asyncio>=0.21.0; extra == "dev"
Requires-Dist: ruff>=0.1.6; extra == "dev"
Requires-Dist: black>=23.11.0; extra == "dev"
Requires-Dist: mypy>=1.7.0; extra == "dev"
Requires-Dist: types-requests>=2.31.0; extra == "dev"
Requires-Dist: pre-commit>=3.5.0; extra == "dev"
Requires-Dist: requests>=2.31.0; extra == "dev"
Dynamic: license-file
